setup.py
balance_mange_trade_ex_forex_next3/__init__.py
balance_mange_trade_ex_forex_next3/balance_mange_trade_ex_forex_next3.py
balance_mange_trade_ex_forex_next3.egg-info/PKG-INFO
balance_mange_trade_ex_forex_next3.egg-info/SOURCES.txt
balance_mange_trade_ex_forex_next3.egg-info/dependency_links.txt
balance_mange_trade_ex_forex_next3.egg-info/not-zip-safe
balance_mange_trade_ex_forex_next3.egg-info/top_level.txt