Metadata-Version: 1.0
Name: balance-mange-trade-ex-forex-next3
Version: 1.2
Summary: balance_mange_trade_ex_forex_next3
Home-page: UNKNOWN
Author: omid
Author-email: UNKNOWN
License: UNKNOWN
Platform: UNKNOWN
